meshtal_analysis/__init__.py
meshtal_analysis/meshtal_analysis.py
meshtal_analysis/meshtal_operator.py
meshtal_analysis-0.3.5.dist-info/METADATA
meshtal_analysis-0.3.5.dist-info/WHEEL
meshtal_analysis-0.3.5.dist-info/entry_points.txt
meshtal_analysis-0.3.5.dist-info/top_level.txt
meshtal_analysis-0.3.5.dist-info/RECORD
