Metadata-Version: 2.1
Name: meshtal-analysis
Version: 0.3.5
Summary: MCNP meshtal output file analysis tool
Home-page: https://github.com/zxkjack123/meshtal_analysis.git
Author: Xiaokang Zhang
Author-email: zxkjack123@163.com
License: MIT
Platform: UNKNOWN
Classifier: Programming Language :: Python :: 3
Classifier: License :: OSI Approved :: MIT License
Classifier: Operating System :: POSIX :: Linux
Classifier: Environment :: Console
